Computer_Ogranisation_Lab/Tutorials/Assgn_5_Grp_54/part_1/alu4BIT.sv
// MODULE FOR FULL ADDER
module add(input a, input b,input cin, output cout, output s,output p,output g);
    assign s=a^b^cin;
    assign cout=(a&b)+(cin&(a^b));
    assign p = a^b;
    assign g = a&b;
endmodule

module carryLookAhead(
    input c0,
    input p0,input g0,
    input p1,input g1,
    input p2,input g2,
    input p3,input g3,
    output [4:0]carry,
    output pg,output gg
);
    assign carry[0]=c0;
    assign carry[1]=g0|(p0&c0);
    assign carry[2]=g1|(p1&g0)|(p1&p0&c0);
    assign carry[3]=g2|(p2&g1)|(p2&p1&g0)|(p2&p1&p0&c0);
    assign carry[4]=g3|(p3&g2)|(p3&p2&g1)|(p3&p2&p1&g0)|(p3&p2&p1&p0&c0);
    assign pg=p0&p1&p2&p3;
    assign gg=g3|(p3&g2)|(p3&p2&g1)|(p3&p2&p1&g0);

endmodule

module carryLookAhead4bit(input [3:0]a,input [3:0]b,input cin,output [3:0]sum,output pg,output gg,output c4);
    wire [3:0] p;   //storing the p's
    wire [3:0] g;   //storing the g's
    wire [4:0] carry; //generate the carry's
    wire temp;  
    assign temp = 0 ; //dump value to operate the addition function
    genvar i;
    //copying full adder circuit 4 times
    generate
        for(i=0;i<4;i=i+1)
        begin
            add fa(a[i],b[i],carry[i],temp,sum[i],p[i],g[i]);
        end
    endgenerate
    
    //connecting with the CARRY LOOK AHEAD UNIT

    carryLookAhead unit(
        cin,
        p[0],g[0],
        p[1],g[1],
        p[2],g[2],
        p[3],g[3],
        carry,
        pg,gg

    );
    assign c4=carry[4];

endmodule

module alu(
		input[3:0]A,B,ALU_Sel,
		input M, cin,
		output Cn4,equality_check,P,G,
  		output [3:0] F
	);
  wire [3:0]ALU_Result;
  reg eq_check;
  assign F = ~(ALU_Result[3:0]);
  wire cout;
  assign Cn4 = ~cout;
  assign equality_check = eq_check;
  
  reg [0:0] Cn;
  
  reg [3:0] op1, op2;
  
  carryLookAhead4bit m1(op1,op2,Cn,ALU_Result,P,G,cout);
  
  
  always @( A or B)
    begin
      if(A==B) begin
        eq_check = 1;
      end
      else begin
        eq_check = 0;
      end
    end
  
  always @(*)
    begin
      case(ALU_Sel) 
        4'b0000: 
            begin
              if(M) begin
                op1 = ~A;
                op2 = 0;
                Cn = 0;
              end
              else begin
                op1 = A;
                op2 = 0;
                Cn = ~cin;

              end
            end
          4'b0001: 
            begin
              if(M) begin
                op1 = ~(A|B);
                op2 = 0;
                Cn = 0;
              end
              else begin
                op1 = A;
                op2 = B;
                Cn = ~cin;

              end
            end
          4'b0010: 
            begin
              if(M) begin
                op1 = (~A)&(B);
                op2 = 0;
                Cn = 0;
              end
              else begin
                op1 = A;
                op2 = ~B;
                Cn = ~cin;

              end
            end
          4'b0011:
            begin
              if(M)begin
                op1 = 0;
                op2 = 0;
                Cn = 0;
              end
              else begin
                op1 = 4'b1111;
                op2 = 0;
                Cn = ~cin;

              end
            end
          4'b0100: 
            begin
              if(M)begin
                op1 = ~(A & B);
                op2 = 0;
                Cn = 0;
              end
              else begin
                op1 = A;
                op2 = A&(~B);
                Cn = ~cin;

              end
            end
           4'b0101:
            begin
              if(M)begin
                op1 = ~B;
                op2 = 0;
                Cn = 0;
              end
              else begin
                op1 = A|B;
                op2 = (A)&(~B);
                Cn = ~cin;

              end
            end
           4'b0110:
            begin
              if(M)begin
                op1 = A^B;
                op2 = 0;
                Cn = 0;
              end
              else begin
                op1 = A;
                op2 = B+1;
                Cn = ~cin;

              end
            end
           4'b0111:
            begin
              if(M)begin
                op1 = A&(~B);
                op2 = 0;
                Cn = 0;
              end
              else begin
                op1 = A&B;
                op2 = 4'b1111;
                Cn = ~cin;
              end
             end
            4'b1000:
             begin
              if(M)begin
                op1 = (~A) | B;
                op2 = 0;
                Cn = 0;
              end
              else begin
                op1 = A&B;
                op2 = A;
                Cn = ~cin;
              end
             end
            4'b1001:  
              begin
              if(M)begin
                op1 = (~A)^(~B);
                op2 = 0;
                Cn = 0;
              end
              else begin
                op1 = A;
                op2 = B;
                Cn = ~cin;
              end
             end
            4'b1010: 
             begin
              if(M)begin
                op1 = 0;
                op2 = B;
                Cn = 0;
              end
              else begin
                op1 = A | (~B);
                op2 = A&B;
                Cn = ~cin;
              end
             end
            4'b1011: 
             begin
              if(M)begin
                op1 = A&B;
                op2 = 0;
                Cn = 0;
              end
              else begin
                op1 = A&B;
                op2 = 4'b1111;
                Cn = ~cin;
              end
             end
            4'b1100:  
             begin
              if(M)begin
                op1 = 0;
                op2 = 1;
                Cn = 0;
              end
              else begin
                op1 = A;
                op2 = A;
                Cn = ~cin;
              end
             end
            4'b1101:
             begin
              if(M)begin
                op1 = A|(~B);
                op2 = 0;
                Cn = 0;
              end
              else begin
                op1 = A|B;
                op2 = A;
                Cn = ~cin;
              end
             end             
            4'b1110: 
             begin
              if(M)begin
                op1 = A&B;
                op2 = 0;
                Cn = 0;
              end
              else begin
                op1 = A&B;
                op2 = A;
                Cn = ~cin;
              end
             end
            4'b1111: 
             begin
              if(M)begin
                op1 = A;
                op2 = 0;
                Cn = 0;
              end
              else begin
                op1 = A|(~B);
                op2 = A;
                Cn = ~cin;
              end
             end
        endcase
    end
      
endmodule

Computer_Ogranisation_Lab/Tutorials/Assgn_5_Grp_54/part_1/testbench.sv
// Code your testbench here
// or browse Examples
module tb_alu;
//Inputs
  reg[3:0] A,B;
  reg[3:0] ALU_Sel;
  reg M, cin;
  //outputs
  wire Cn4, equality_check,P,G;
  wire [3:0] F;
 // Verilog code for ALU
 integer i;
 alu test_unit(
            A,B,  // ALU 8-bit Inputs                 
            ALU_Sel,// ALU Selection
   			M,cin,
   			Cn4,equality_check,P,G,F
     );
    initial begin
    // hold reset state for 100 ns.
      
      $dumpfile("test.vcd");
      $dumpvars;

      A = 4'b1101;
      B = 4'b0101;
      cin = 1;
      M = 1;
      ALU_Sel = 4'h0;
      $monitor("A = %b, B = %b, ALU_Select = %b, Cn = %b, M = %b, F = %b, eq_check = %b, cout = %b", A, B, ALU_Sel, cin, M, F, equality_check, Cn4);
      for (i=0;i<=15;i=i+1)
      begin
       ALU_Sel = ALU_Sel + 8'h01;
       M = ~M;
       #10;
      end
      
    end
endmodule

Computer_Ogranisation_Lab/Tutorials/Assgn_5_Grp_54/part_1/test.vcd
$date
	Tue Oct 13 18:00:45 2020
$end
$version
	Icarus Verilog
$end
$timescale
	1s
$end
$scope module tb_alu $end
$var wire 1 ! equality_check $end
$var wire 1 " P $end
$var wire 1 # G $end
$var wire 4 $ F [3:0] $end
$var wire 1 % Cn4 $end
$var reg 4 & A [3:0] $end
$var reg 4 ' ALU_Sel [3:0] $end
$var reg 4 ( B [3:0] $end
$var reg 1 ) M $end
$var reg 1 * cin $end
$var integer 32 + i [31:0] $end
$scope module test_unit $end
$var wire 4 , A [3:0] $end
$var wire 4 - ALU_Sel [3:0] $end
$var wire 4 . B [3:0] $end
$var wire 1 % Cn4 $end
$var wire 4 / F [3:0] $end
$var wire 1 ) M $end
$var wire 1 * cin $end
$var wire 1 ! equality_check $end
$var wire 1 0 cout $end
$var wire 1 " P $end
$var wire 1 # G $end
$var wire 4 1 ALU_Result [3:0] $end
$var reg 1 2 Cn $end
$var reg 1 3 eq_check $end
$var reg 4 4 op1 [3:0] $end
$var reg 4 5 op2 [3:0] $end
$scope module m1 $end
$var wire 4 6 a [3:0] $end
$var wire 4 7 b [3:0] $end
$var wire 1 2 cin $end
$var wire 1 8 temp $end
$var wire 4 9 sum [3:0] $end
$var wire 1 " pg $end
$var wire 4 : p [3:0] $end
$var wire 1 # gg $end
$var wire 4 ; g [3:0] $end
$var wire 5 < carry [4:0] $end
$var wire 1 0 c4 $end
$scope begin genblk1[0] $end
$scope module fa $end
$var wire 1 = a $end
$var wire 1 > b $end
$var wire 1 ? cin $end
$var wire 1 8 cout $end
$var wire 1 @ g $end
$var wire 1 A p $end
$var wire 1 B s $end
$upscope $end
$upscope $end
$scope begin genblk1[1] $end
$scope module fa $end
$var wire 1 C a $end
$var wire 1 D b $end
$var wire 1 E cin $end
$var wire 1 8 cout $end
$var wire 1 F g $end
$var wire 1 G p $end
$var wire 1 H s $end
$upscope $end
$upscope $end
$scope begin genblk1[2] $end
$scope module fa $end
$var wire 1 I a $end
$var wire 1 J b $end
$var wire 1 K cin $end
$var wire 1 8 cout $end
$var wire 1 L g $end
$var wire 1 M p $end
$var wire 1 N s $end
$upscope $end
$upscope $end
$scope begin genblk1[3] $end
$scope module fa $end
$var wire 1 O a $end
$var wire 1 P b $end
$var wire 1 Q cin $end
$var wire 1 8 cout $end
$var wire 1 R g $end
$var wire 1 S p $end
$var wire 1 T s $end
$upscope $end
$upscope $end
$scope module unit $end
$var wire 1 2 c0 $end
$var wire 1 U g0 $end
$var wire 1 V g1 $end
$var wire 1 W g2 $end
$var wire 1 X g3 $end
$var wire 1 # gg $end
$var wire 1 Y p0 $end
$var wire 1 Z p1 $end
$var wire 1 [ p2 $end
$var wire 1 \ p3 $end
$var wire 1 " pg $end
$var wire 5 ] carry [4:0] $end
$upscope $end
$upscope $end
$upscope $end
$upscope $end
$enddefinitions $end
#0
$dumpvars
b11010 ]
1\
0[
0Z
0Y
0X
1W
0V
1U
0T
1S
0R
1Q
0P
1O
0N
0M
1L
0K
1J
1I
1H
0G
0F
1E
0D
0C
0B
0A
1@
0?
1>
1=
b11010 <
b101 ;
b1000 :
b10 9
x8
b101 7
b1101 6
b101 5
b1101 4
03
02
b10 1
10
b1101 /
b101 .
b1 -
b1101 ,
b0 +
1*
0)
b101 (
b1 '
b1101 &
0%
b1101 $
1#
0"
0!
$end
#10
1%
00
0Q
0#
0H
0E
b0 <
b0 ]
b1111 $
b1111 /
0U
0W
b0 1
b0 9
0T
08
0\
0@
b0 ;
0L
b0 :
0S
0>
0J
0=
0I
0O
b0 5
b0 7
b0 4
b0 6
1)
b10 '
b10 -
b1 +
#20
1"
b0 $
b0 /
1B
1Y
1H
1Z
1N
1[
b1111 1
b1111 9
1T
1\
1A
1G
1M
b1111 :
1S
1=
1C
1I
1O
b1111 4
b1111 6
0)
b11 '
b11 -
b10 +
#30
0"
b101 $
b101 /
0B
0Y
b1010 1
b1010 9
0N
0[
0A
b1010 :
0M
0=
0I
b1010 4
b1010 6
1)
b100 '
b100 -
b11 +
#40
0%
10
b10000 <
b10000 ]
1#
b1010 $
b1010 /
0T
0\
1X
1B
1Y
0H
0Z
b101 1
b101 9
1N
1[
x8
0S
b1000 ;
1R
1A
0G
b101 :
1M
1P
1=
0C
1I
b1000 5
b1000 7
b1101 4
b1101 6
0)
b101 '
b101 -
b100 +
#50
1%
00
b0 <
b0 ]
0#
b111 $
b111 /
1T
1\
0X
0B
0Y
b1000 1
b1000 9
0N
0[
08
1S
b0 ;
0R
0A
b1000 :
0M
0P
0=
0I
b0 5
b0 7
b1000 4
b1000 6
1)
b110 '
b110 -
b101 +
#60
0%
10
1N
0T
1K
1Q
1#
1E
b1011 $
b1011 /
b11110 <
b11110 ]
b100 1
b100 9
0H
1Z
1U
1W
b1010 :
1G
1@
x8
b101 ;
1L
1>
1D
1J
1P
1=
1I
0O
b1111 5
b1111 7
b101 4
b101 6
0)
b111 '
b111 -
b110 +
#70
1%
00
08
0K
0Q
0#
1H
0E
b0 <
b0 ]
b1000 $
b1000 /
1B
1Y
0U
1N
1[
0W
b111 1
b111 9
0T
0\
1A
0@
1M
b0 ;
0L
b111 :
0S
0>
0D
0J
0P
1C
b0 5
b0 7
b111 4
b111 6
1)
b1000 '
b1000 -
b111 +
#80
0%
10
1Q
1#
1E
b11010 <
b11010 ]
b1101 $
b1101 /
0"
0B
0Y
1U
0N
0[
1W
1H
0Z
b10 1
b10 9
0T
1\
0A
1@
x8
0M
b101 ;
1L
0G
b1000 :
1S
1>
1J
0C
1O
b101 5
b101 7
b1101 4
b1101 6
0)
b1001 '
b1001 -
b1000 +
#90
1%
00
0Q
0#
0H
0E
b0 <
b0 ]
b1010 $
b1010 /
1B
1Y
0U
1N
1[
0W
b101 1
b101 9
0T
08
0\
1A
0@
1M
b0 ;
0L
b101 :
0S
0=
0I
0O
b0 4
b0 6
1)
b1010 '
b1010 -
b1001 +
#100
0%
10
1K
1Q
1#
1E
b11110 <
b11110 ]
b1011 $
b1011 /
0H
1Z
0T
1\
0B
0Y
1U
b100 1
b100 9
1N
0[
1W
1G
1S
0A
1@
x8
b1010 :
0M
b101 ;
1L
1D
1P
1=
1I
b1111 5
b1111 7
b101 4
b101 6
0)
b1011 '
b1011 -
b1010 +
#110
1%
00
0N
0K
0Q
0#
0E
b1110 $
b1110 /
b0 <
b0 ]
0H
08
0Z
0T
0\
b1 1
b1 9
1B
1Y
0U
0W
0G
0S
b1 :
1A
0@
b0 ;
0L
0D
0J
0P
0=
0I
b1 5
b1 7
b0 4
b0 6
1)
b1100 '
b1100 -
b1011 +
#120
0%
1T
10
1Q
1H
1#
1E
b101 $
b101 /
b11010 <
b11010 ]
b1010 1
b1010 9
0B
0Y
1U
1W
1X
b0 :
0A
1@
1L
x8
b1101 ;
1R
1J
1P
1=
1I
1O
b1101 5
b1101 7
b1101 4
b1101 6
0)
b1101 '
b1101 -
b1100 +
#130
1%
0T
00
0Q
0H
0#
0E
b0 <
b0 ]
b1010 $
b1010 /
1B
1Y
0U
b101 1
b101 9
1N
1[
0W
0X
08
1A
0@
b101 :
1M
0L
b0 ;
0R
0>
0J
0P
0O
b0 5
b0 7
b101 4
b101 6
1)
b1110 '
b1110 -
b1101 +
#140
0%
1T
10
1Q
1K
1#
1E
b11110 <
b11110 ]
b11 $
b11 /
0B
0Y
1U
1N
0[
1W
b1100 1
b1100 9
0H
1Z
1X
0A
1@
0M
1L
b10 :
1G
x8
b1101 ;
1R
1>
1J
1P
1C
1O
b1101 5
b1101 7
b1111 4
b1111 6
0)
b1111 '
b1111 -
b1110 +
#150
1%
0N
0T
00
b1101 $
b1101 /
0K
0Q
b10 1
b10 9
1H
08
0#
0E
b0 <
b0 ]
0U
0W
0X
0@
0L
b0 ;
0R
0>
0J
0P
0=
0I
0O
b0 5
b0 7
b10 4
b10 6
1)
b0 '
b0 -
b1111 +
#160
b10000 +
